sparc/__init__.py
sparc/process_puzzle.py
sparc/prompt.py
sparc/prompts/__init__.py
sparc/prompts/gym_step.py
sparc/prompts/gym_step_traceback.py
sparc/prompts/gym_visual.py
sparc/prompts/gym_visual_traceback.py
sparc/prompts/single_shot.py
sparc/prompts/single_shot_visual.py
sparc/sparc.py
sparc/tables.py
sparc/validation.py
sparc_puzzle-0.5.2.dist-info/METADATA
sparc_puzzle-0.5.2.dist-info/WHEEL
sparc_puzzle-0.5.2.dist-info/entry_points.txt
sparc_puzzle-0.5.2.dist-info/licenses/LICENCE
sparc_puzzle-0.5.2.dist-info/RECORD
