Metadata-Version: 2.4
Name: sparc-puzzle
Version: 0.5.2
Summary: 
License-File: LICENCE
Author: larskaesberg
Author-email: larskaesberg@gmail.com
Requires-Python: >=3.10
Classifier: Programming Language :: Python :: 3
Classifier: Programming Language :: Python :: 3.10
Classifier: Programming Language :: Python :: 3.11
Classifier: Programming Language :: Python :: 3.12
Classifier: Programming Language :: Python :: 3.13
Classifier: Programming Language :: Python :: 3.14
Requires-Dist: datasets (>=3.6.0)
Requires-Dist: openai (>=2.7.1,<3.0.0)
Requires-Dist: rich (>=13.0.0,<14.0.0)
Requires-Dist: sparc-gym (>=0.2.5,<0.3.0)
Requires-Dist: sparc-visualization (>=0.1.3)
Requires-Dist: tqdm (>=4.60.0,<5.0.0)
